r_torch/__init__.py
r_torch/main.py
r_torch-0.0.3.dist-info/LICENSE
r_torch-0.0.3.dist-info/METADATA
r_torch-0.0.3.dist-info/WHEEL
r_torch-0.0.3.dist-info/RECORD
